{"cameraMode":{"drawMode":0,"name":"Shaded","section":"Shading Mode"},"sceneLighting":true,"audioPlay":false,"sceneViewState":{"m_AlwaysRefresh":false,"showFog":true,"showSkybox":true,"showFlares":true,"showImageEffects":true,"showParticleSystems":true,"showVisualEffectGraphs":true,"m_FxEnabled":true},"in2DMode":false,"pivot":{"x":85.19998931884766,"y":-59.40220260620117,"z":-4.47038459777832},"rotation":{"x":-0.09332104027271271,"y":0.7449955344200134,"z":-0.6518447995185852,"w":-0.10665807127952576},"size":39.25306701660156,"orthographic":false}